{
  "providers": [
    {
      "type": "space",
      "advances": {
        " ": 4
      }
    },
    {
      "type": "bitmap",
      "file": "dodgebolters:fonts/actionbar/coins.png",
      "chars": ["c"],
      "ascent": -22,
      "height": 14
    },
    {
      "type": "bitmap",
      "file": "dodgebolters:fonts/actionbar/crowns.png",
      "chars": ["C"],
      "ascent": -22,
      "height": 14
    },
    {
      "type": "bitmap",
      "file": "dodgebolters:logo/red_long.png",
      "chars": ["L"],
      "ascent": 18,
      "height": 18.5
    }
  ]
}
